super_py/__init__.py
super_py/concurrency.py
super_py/dicts.py
super_py/disk.py
super_py/logging.py
super_py/string.py
super_py/testing.py
super_py-1.0.3.dist-info/LICENSE
super_py-1.0.3.dist-info/WHEEL
super_py-1.0.3.dist-info/METADATA
super_py-1.0.3.dist-info/RECORD
