Metadata-Version: 2.1
Name: super-py
Version: 1.0.3
Summary: Features that Python should have in the standard library
Home-page: https://github.com/mkrd/SuperPy
License: MIT
Author: Marcel Kröker
Author-email: kroeker.marcel@gmail.com
Requires-Python: >=3.8,<4.0
Classifier: Intended Audience :: Developers
Classifier: License :: OSI Approved :: MIT License
Classifier: Operating System :: OS Independent
Classifier: Programming Language :: Python
Classifier: Programming Language :: Python :: 3
Classifier: Programming Language :: Python :: 3.8
Classifier: Programming Language :: Python :: 3.9
Classifier: Programming Language :: Python :: 3.10
Classifier: Programming Language :: Python :: 3.11
Classifier: Programming Language :: Python :: 3
Classifier: Topic :: Software Development :: Libraries :: Python Modules
Project-URL: Repository, https://github.com/mkrd/SuperPy
